Metadata-Version: 2.4
Name: package_imagens
Version: 0.0.1
Summary: Um pacote para processamento básico de imagens
Home-page: https://github.com/DrySiqu3ira/simple-package-template
Author: Adrienne Siqueira
Author-email: adrienne_siqueira97@hotmail.com
License: MIT
Keywords: imagens processamento opencv pil
Classifier: Programming Language :: Python :: 3
Classifier: License :: OSI Approved :: MIT License
Classifier: Operating System :: OS Independent
Requires-Python: >=3.8
Dynamic: author
Dynamic: author-email
Dynamic: classifier
Dynamic: description
Dynamic: description-content-type
Dynamic: home-page
Dynamic: keywords
Dynamic: license
Dynamic: requires-python
Dynamic: summary
